ensphere/__init__.py
ensphere/__main__.py
ensphere-0.3.dist-info/DESCRIPTION.rst
ensphere-0.3.dist-info/METADATA
ensphere-0.3.dist-info/RECORD
ensphere-0.3.dist-info/WHEEL
ensphere-0.3.dist-info/entry_points.txt
ensphere-0.3.dist-info/metadata.json
ensphere-0.3.dist-info/top_level.txt
