Metadata-Version: 2.0
Name: ensphere
Version: 0.3
Summary: Add XMP metadata for PanoSphere in the pictures.
Home-page: https://github.com/vitroid/ensphere/
Author: Masakazu Matsumoto
Author-email: vitroid@gmail.com
License: MIT
Keywords: ensphere,panorama,equirectangular,photosphere,XMPmetadata
Platform: UNKNOWN
Classifier: Development Status :: 4 - Beta
Classifier: Intended Audience :: Developers
Classifier: Programming Language :: Python
Classifier: Programming Language :: Python :: 2.7
Requires-Dist: imagesize
Requires-Dist: python-xmp-toolkit
